torchic/__init__.py
torchic/nn/__init__.py
torchic/nn/builder/__init__.py
torchic/nn/layers/__init__.py
torchic/nn/trainers/__init__.py
torchic/utils/__init__.py
pytorchic-5.0.1.dist-info/LICENSE
pytorchic-5.0.1.dist-info/METADATA
pytorchic-5.0.1.dist-info/WHEEL
pytorchic-5.0.1.dist-info/RECORD
