Metadata-Version: 2.1
Name: pytorchic
Version: 5.0.1
Summary: A framework for instantly building flexible PyTorch models.
License: MIT
Author: Mattia Matteini
Author-email: matteinimattia@gmail.com
Requires-Python: >=3.10,<4.0
Classifier: License :: OSI Approved :: MIT License
Classifier: Programming Language :: Python :: 3
Classifier: Programming Language :: Python :: 3.10
Classifier: Programming Language :: Python :: 3.11
Classifier: Programming Language :: Python :: 3.12
Classifier: Programming Language :: Python :: 3.13
Requires-Dist: coverage (>=7.8.0,<8.0.0)
Requires-Dist: matplotlib (>=3.10.1,<4.0.0)
Requires-Dist: mypy (>=1.15.0,<2.0.0)
Requires-Dist: pytest (>=8.3.5,<9.0.0)
Requires-Dist: ruff (>=0.11.6,<0.12.0)
Requires-Dist: torch (>=2.7.0,<3.0.0)
